accelbyte_py_sdk/api/chat/__init__.py
accelbyte_py_sdk/api/chat/errors.py
accelbyte_py_sdk/api/chat/models/__init__.py
accelbyte_py_sdk/api/chat/models/api_add_member_params.py
accelbyte_py_sdk/api/chat/models/api_create_namespace_topic_params.py
accelbyte_py_sdk/api/chat/models/api_create_topic_params.py
accelbyte_py_sdk/api/chat/models/api_create_topic_response.py
accelbyte_py_sdk/api/chat/models/api_mute_user_request.py
accelbyte_py_sdk/api/chat/models/api_muted_topic_response.py
accelbyte_py_sdk/api/chat/models/api_send_chat_params.py
accelbyte_py_sdk/api/chat/models/api_unmute_user_request.py
accelbyte_py_sdk/api/chat/models/api_update_topic_params.py
accelbyte_py_sdk/api/chat/models/log_app_message_declaration.py
accelbyte_py_sdk/api/chat/models/logconfig_configuration.py
accelbyte_py_sdk/api/chat/models/message_action_add_user_to_topic_result.py
accelbyte_py_sdk/api/chat/models/message_action_delete_topic_result.py
accelbyte_py_sdk/api/chat/models/models_add_inbox_category_request.py
accelbyte_py_sdk/api/chat/models/models_add_inbox_category_response.py
accelbyte_py_sdk/api/chat/models/models_ban_topic_member_param.py
accelbyte_py_sdk/api/chat/models/models_ban_topic_member_result.py
accelbyte_py_sdk/api/chat/models/models_category_hook.py
accelbyte_py_sdk/api/chat/models/models_channel_topic_response.py
accelbyte_py_sdk/api/chat/models/models_channel_topic_summary_response.py
accelbyte_py_sdk/api/chat/models/models_channel_topic_with_pagination_response.py
accelbyte_py_sdk/api/chat/models/models_chat_message_response.py
accelbyte_py_sdk/api/chat/models/models_chat_message_with_pagination_response.py
accelbyte_py_sdk/api/chat/models/models_chat_snapshot_message.py
accelbyte_py_sdk/api/chat/models/models_chat_snapshots.py
accelbyte_py_sdk/api/chat/models/models_config.py
accelbyte_py_sdk/api/chat/models/models_config_export.py
accelbyte_py_sdk/api/chat/models/models_config_list.py
accelbyte_py_sdk/api/chat/models/models_config_response.py
accelbyte_py_sdk_service_chat-0.25.0.dist-info/METADATA
accelbyte_py_sdk_service_chat-0.25.0.dist-info/WHEEL
accelbyte_py_sdk_service_chat-0.25.0.dist-info/top_level.txt
accelbyte_py_sdk_service_chat-0.25.0.dist-info/RECORD
