Metadata-Version: 2.4
Name: accelbyte-py-sdk-service-chat
Version: 0.25.0
Summary: AccelByte Python SDK - AccelByte Gaming Services Chat Service
Requires-Python: >=3.9
Requires-Dist: accelbyte-py-sdk-core
